pythermalgreen/__init__.py
pythermalgreen/main.py
pythermalgreen-0.2.6.dist-info/LICENSE
pythermalgreen-0.2.6.dist-info/METADATA
pythermalgreen-0.2.6.dist-info/WHEEL
pythermalgreen-0.2.6.dist-info/entry_points.txt
pythermalgreen-0.2.6.dist-info/top_level.txt
pythermalgreen-0.2.6.dist-info/RECORD
