Metadata-Version: 2.1
Name: pythermalgreen
Version: 0.2.6
Author: Guilherme Landim-Santos
Author-email: guisaan.gui@gmail.com
License-File: LICENSE
Requires-Dist: numpy >=1.22.0
Requires-Dist: rasterio ==1.3.10
Requires-Dist: geopandas ==0.14.4
Requires-Dist: pandas <=2.2.2
Requires-Dist: shapely ==2.0.4
Requires-Dist: pylandstats ==2.4.2
